spt_neo_rag_client/__init__.py
spt_neo_rag_client/_admin.py
spt_neo_rag_client/_api_keys.py
spt_neo_rag_client/_bm25.py
spt_neo_rag_client/_content.py
spt_neo_rag_client/_dashboard.py
spt_neo_rag_client/_documents.py
spt_neo_rag_client/_health.py
spt_neo_rag_client/_knowledge_bases.py
spt_neo_rag_client/_knowledge_graph.py
spt_neo_rag_client/_models.py
spt_neo_rag_client/_queries.py
spt_neo_rag_client/_raptor.py
spt_neo_rag_client/_settings.py
spt_neo_rag_client/_structured_schemas.py
spt_neo_rag_client/_tasks.py
spt_neo_rag_client/_teams.py
spt_neo_rag_client/_users.py
spt_neo_rag_client/_webhooks.py
spt_neo_rag_client/auth.py
spt_neo_rag_client/client.py
spt_neo_rag_client/exceptions.py
spt_neo_rag_client/models.py
spt_neo_rag_client-0.6.0.dist-info/METADATA
spt_neo_rag_client-0.6.0.dist-info/WHEEL
spt_neo_rag_client-0.6.0.dist-info/RECORD
