Metadata-Version: 2.1
Name: spt-neo-rag-client
Version: 0.6.0
Summary: Client library for SPT Neo RAG API
Project-URL: Homepage, https://github.com/sponge-theory/spt-neo-rag
Project-URL: Documentation, https://github.com/sponge-theory/spt-neo-rag/tree/main/clients/spt-neo-rag-client
Project-URL: Bug Tracker, https://github.com/sponge-theory/spt-neo-rag/issues
Project-URL: Source Code, https://github.com/sponge-theory/spt-neo-rag/tree/main/clients/spt-neo-rag-client
Author-email: SPT Neo RAG Team <contact@sponge-theory.ai>
License: MIT
Classifier: Development Status :: 4 - Beta
Classifier: Intended Audience :: Developers
Classifier: License :: OSI Approved :: MIT License
Classifier: Programming Language :: Python :: 3
Classifier: Programming Language :: Python :: 3.9
Classifier: Programming Language :: Python :: 3.10
Classifier: Programming Language :: Python :: 3.11
Classifier: Programming Language :: Python :: 3.12
Classifier: Topic :: Internet :: WWW/HTTP :: Dynamic Content
Classifier: Topic :: Scientific/Engineering :: Artificial Intelligence
Classifier: Topic :: Software Development :: Libraries :: Python Modules
Requires-Python: >=3.9
Requires-Dist: httpx>=0.24.0
Requires-Dist: pydantic>=2.0.0
Requires-Dist: pydantic[email]>=2.0.0
Requires-Dist: python-jose>=3.3.0
Requires-Dist: python-multipart>=0.0.5
Provides-Extra: dev
Requires-Dist: black>=23.3.0; extra == 'dev'
Requires-Dist: isort>=5.12.0; extra == 'dev'
Requires-Dist: mypy>=1.3.0; extra == 'dev'
Requires-Dist: pytest-asyncio>=0.21.0; extra == 'dev'
Requires-Dist: pytest>=7.3.1; extra == 'dev'
Requires-Dist: ruff>=0.0.269; extra == 'dev'
